MANIFEST.in
README.rst
setup.py
pdt/__init__.py
pdt/build-cdn.sh
pdt/chop_nppes_public.py
pdt/combine_nppes_pecos_org_fhir.py
pdt/combine_nppes_pecos_pract_fhir.py
pdt/create_combined_indexes.py
pdt/create_pecos_compiled_indexes.py
pdt/create_pecos_indexes.py
pdt/create_provider_indexes.py
pdt/csv2fhir_public.py
pdt/csv2mlvs.py
pdt/csv2pjson_public.py
pdt/json_schema_check.py
pdt/json_schema_check_fhir.py
pdt/load_nppes_and_pecos.py
pdt/load_pecos.py
pdt/loadnppes.py
pdt/makepecosdocs.py
pdt/makepecosfhir.py
pdt/nucc_taxonomy_160.csv
pdt/nucc_taxonomy_201.csv
pdt/pull_new_files_ready.py
pdt/pull_pecos.py
pdt/split_practitioners_and_organizations.py
pdt/vnpi.py
pdt.egg-info/PKG-INFO
pdt.egg-info/SOURCES.txt
pdt.egg-info/dependency_links.txt
pdt.egg-info/requires.txt
pdt.egg-info/top_level.txt
pdt/fhir_json_schema/Organization.json
pdt/fhir_json_schema/Practitioner.json
pdt/fhir_json_schema/__init__.py
pdt/pjson/__init__.py
pdt/pjson/choices.py
pdt/pjson/validate_addresses.py
pdt/pjson/validate_affiliations.py
pdt/pjson/validate_basic.py
pdt/pjson/validate_direct_addresses.py
pdt/pjson/validate_identifiers.py
pdt/pjson/validate_licenses.py
pdt/pjson/validate_other_names.py
pdt/pjson/validate_pjson
pdt/pjson/validate_pjson.py
pdt/pjson/validate_pjson_affiliations
pdt/pjson/validate_pjson_dir
pdt/pjson/validate_taxonomies.py
tests/__init__.py
tests/context.py
tests/first10.csv
tests/test_chop_nppes_public.py
tests/test_create_provider_indexes.py
tests/test_csv2fhir_public.py
tests/test_csv2pjson_public.py
tests/test_loadnppes.py
tests/test_vnpi.py