Metadata-Version: 1.1
Name: pdt
Version: 0.8.2.8
Summary: Provider Data Tools
Home-page: https://github.com/TransparentHealth/provider-data-tools
Author: Alan Viars
Author-email: sales@videntity.com
License: UNKNOWN
Download-URL: https://github.com/hhsidealab/provider-data-tools/tarball/master
Platform: UNKNOWN
